day6/day5-carry/chaser_wb.v
module chaser_wb(
    input wire          i_clk,

    input wire          i_cyc,
    input wire          i_stb,
    input wire          i_we,
    input wire          i_addr,
    input wire [31:0]   i_data,
    output wire         o_stall,
    output reg          o_ack,
    output wire [31:0]  o_data,

    output reg  [5:0]   o_led
);
    parameter WIDTH = 24;

    wire            busy;
    reg     [3:0]   state;
    
    initial state = 0;

    // Verilator lint_off UNUSED
    wire [33:0] unused;
    assign unused = { i_cyc, i_addr, i_data };
    // Verilator lint_on UNUSED

    initial o_ack = 1'b0;
    always @(posedge i_clk)
        o_ack <= (i_stb) && (!o_stall);
    
    assign o_stall = (busy) && (i_we);
    assign o_data = { 28'h0, state };

    assign busy = (state != 0);

    always @(posedge i_clk)
    begin
        if ((i_stb) && (i_we) && (!o_stall))
            state <= 4'h1;
        else if (state >= 4'hB)
            state <= 4'h0;
        else if (state != 0)
            state <= state + 1'h1;

        case (state)
            4'h1: o_led <= 6'h01;
            4'h2: o_led <= 6'h02;
            4'h3: o_led <= 6'h04;
            4'h4: o_led <= 6'h08;
            4'h5: o_led <= 6'h10;
            4'h6: o_led <= 6'h20;
            4'h7: o_led <= 6'h10;
            4'h8: o_led <= 6'h08;
            4'h9: o_led <= 6'h04;
            4'hA: o_led <= 6'h02;
            4'hB: o_led <= 6'h01;
            default: o_led <= 6'h00;
        endcase
    end
endmodule

day6/day5-carry/chaser_wb_trace.vcd
$version Generated by VerilatedVcd $end
$date Sat Jun 15 20:08:44 2019
 $end
$timescale   1ns $end

 $scope module TOP $end
  $var wire  1 ) i_addr $end
  $var wire  1 % i_clk $end
  $var wire  1 & i_cyc $end
  $var wire 32 * i_data [31:0] $end
  $var wire  1 ' i_stb $end
  $var wire  1 ( i_we $end
  $var wire  1 , o_ack $end
  $var wire 32 - o_data [31:0] $end
  $var wire  6 . o_led [5:0] $end
  $var wire  1 + o_stall $end
  $scope module chaser_wb $end
   $var wire  1 # busy $end
   $var wire  1 ) i_addr $end
   $var wire  1 % i_clk $end
   $var wire  1 & i_cyc $end
   $var wire 32 * i_data [31:0] $end
   $var wire  1 ' i_stb $end
   $var wire  1 ( i_we $end
   $var wire  1 , o_ack $end
   $var wire 32 - o_data [31:0] $end
   $var wire  6 . o_led [5:0] $end
   $var wire  1 + o_stall $end
   $var wire  4 $ state [3:0] $end
   $var wire 34 / unused [33:0] $end
  $upscope $end
 $upscope $end
$enddefinitions $end


#8
0#
b0000 $
0%
1&
1'
0(
0)
b00000000000000000000000000000000 *
0+
0,
b00000000000000000000000000000000 -
b000000 .
b1000000000000000000000000000000000 /
#10
1%
1,
#15
0%
#18
0&
0'
b0000000000000000000000000000000000 /
#20
1%
0,
#25
0%
#28
#30
1%
#35
0%
#38
#40
1%
#45
0%
#48
#50
1%
#55
0%
#58
#60
1%
#65
0%
#68
1&
1'
1(
b1000000000000000000000000000000000 /
#70
1#
b0001 $
1%
1+
1,
b00000000000000000000000000000001 -
#75
0%
#78
0&
0'
b0000000000000000000000000000000000 /
#80
b0010 $
1%
0,
b00000000000000000000000000000010 -
b000001 .
#85
0%
#88
1&
1'
0(
0+
b1000000000000000000000000000000000 /
#90
b0011 $
1%
1,
b00000000000000000000000000000011 -
b000010 .
#95
0%
#98
0&
0'
b0000000000000000000000000000000000 /
#100
b0100 $
1%
0,
b00000000000000000000000000000100 -
b000100 .
#105
0%
#108
1&
1'
b1000000000000000000000000000000000 /
#110
b0101 $
1%
1,
b00000000000000000000000000000101 -
b001000 .
#115
0%
#118
0&
0'
b0000000000000000000000000000000000 /
#120
b0110 $
1%
0,
b00000000000000000000000000000110 -
b010000 .
#125
0%
#128
1&
1'
b1000000000000000000000000000000000 /
#130
b0111 $
1%
1,
b00000000000000000000000000000111 -
b100000 .
#135
0%
#138
0&
0'
b0000000000000000000000000000000000 /
#140
b1000 $
1%
0,
b00000000000000000000000000001000 -
b010000 .
#145
0%
#148
1&
1'
b1000000000000000000000000000000000 /
#150
b1001 $
1%
1,
b00000000000000000000000000001001 -
b001000 .
#155
0%
#158
0&
0'
b0000000000000000000000000000000000 /
#160
b1010 $
1%
0,
b00000000000000000000000000001010 -
b000100 .
#165
0%
#168
1&
1'
b1000000000000000000000000000000000 /
#170
b1011 $
1%
1,
b00000000000000000000000000001011 -
b000010 .
#175
0%
#178
0&
0'
b0000000000000000000000000000000000 /
#180
0#
b0000 $
1%
0,
b00000000000000000000000000000000 -
b000001 .
#185
0%
#188
1&
1'
b1000000000000000000000000000000000 /
#190
1%
1,
b000000 .
#195
0%
#198
0&
0'
b0000000000000000000000000000000000 /
#200
1%
0,
#205
0%
#208
#210
1%
#215
0%
#218
#220
1%
#225
0%
#228
#230
1%
#235
0%
#238
#240
1%
#245
0%
#248
1&
1'
1(
b1000000000000000000000000000000000 /
#250
1#
b0001 $
1%
1+
1,
b00000000000000000000000000000001 -
#255
0%
#258
0&
0'
b0000000000000000000000000000000000 /
#260
b0010 $
1%
0,
b00000000000000000000000000000010 -
b000001 .
#265
0%
#268
1&
1'
0(
0+
b1000000000000000000000000000000000 /
#270
b0011 $
1%
1,
b00000000000000000000000000000011 -
b000010 .
#275
0%
#278
0&
0'
b0000000000000000000000000000000000 /
#280
b0100 $
1%
0,
b00000000000000000000000000000100 -
b000100 .
#285
0%
#288
1&
1'
b1000000000000000000000000000000000 /
#290
b0101 $
1%
1,
b00000000000000000000000000000101 -
b001000 .
#295
0%
#298
0&
0'
b0000000000000000000000000000000000 /
#300
b0110 $
1%
0,
b00000000000000000000000000000110 -
b010000 .
#305
0%
#308
1&
1'
b1000000000000000000000000000000000 /
#310
b0111 $
1%
1,
b00000000000000000000000000000111 -
b100000 .
#315
0%
#318
0&
0'
b0000000000000000000000000000000000 /
#320
b1000 $
1%
0,
b00000000000000000000000000001000 -
b010000 .
#325
0%
#328
1&
1'
b1000000000000000000000000000000000 /
#330
b1001 $
1%
1,
b00000000000000000000000000001001 -
b001000 .
#335
0%
#338
0&
0'
b0000000000000000000000000000000000 /
#340
b1010 $
1%
0,
b00000000000000000000000000001010 -
b000100 .
#345
0%
#348
1&
1'
b1000000000000000000000000000000000 /
#350
b1011 $
1%
1,
b00000000000000000000000000001011 -
b000010 .
#355
0%
#358
0&
0'
b0000000000000000000000000000000000 /
#360
0#
b0000 $
1%
0,
b00000000000000000000000000000000 -
b000001 .
#365
0%
#368
1&
1'
b1000000000000000000000000000000000 /
#370
1%
1,
b000000 .
